nlptklzxcd/__init__.py
nlptklzxcd/loader.py
nlptklzxcd/data/sample1.txt
nlptklzxcd/data/streamlitx.txt
nlptklzxcd-0.4.2.dist-info/LICENSE
nlptklzxcd-0.4.2.dist-info/METADATA
nlptklzxcd-0.4.2.dist-info/WHEEL
nlptklzxcd-0.4.2.dist-info/top_level.txt
nlptklzxcd-0.4.2.dist-info/RECORD
